CHANGES.txt
README.txt
bootstrap.py
buildout.cfg
setup.py
src/zope/__init__.py
src/zope.app.cache.egg-info/PKG-INFO
src/zope.app.cache.egg-info/SOURCES.txt
src/zope.app.cache.egg-info/dependency_links.txt
src/zope.app.cache.egg-info/namespace_packages.txt
src/zope.app.cache.egg-info/not-zip-safe
src/zope.app.cache.egg-info/requires.txt
src/zope.app.cache.egg-info/top_level.txt
src/zope/app/__init__.py
src/zope/app/cache/__init__.py
src/zope/app/cache/annotationcacheable.py
src/zope/app/cache/caching.py
src/zope/app/cache/configure.zcml
src/zope/app/cache/ram.py
src/zope/app/cache/browser/__init__.py
src/zope/app/cache/browser/cacheable.py
src/zope/app/cache/browser/cacheableedit.pt
src/zope/app/cache/browser/configure.zcml
src/zope/app/cache/browser/ram.py
src/zope/app/cache/browser/ramedit.pt
src/zope/app/cache/browser/ramstats.pt
src/zope/app/cache/interfaces/__init__.py
src/zope/app/cache/interfaces/ram.py
src/zope/app/cache/tests/__init__.py
src/zope/app/cache/tests/test_annotationcacheable.py
src/zope/app/cache/tests/test_caching.py
src/zope/app/cache/tests/test_icache.py
src/zope/app/cache/tests/test_ramcache.py